MANIFEST.in
README
README.md
UIP
mac-requirements.txt
requirements.txt
setup.py
UIP.egg-info/PKG-INFO
UIP.egg-info/SOURCES.txt
UIP.egg-info/dependency_links.txt
UIP.egg-info/entry_points.txt
UIP.egg-info/requires.txt
UIP.egg-info/top_level.txt
uiplib/GUI.py
uiplib/UIP.py
uiplib/__init__.py
uiplib/scheduler.py
uiplib/setWallpaper.py
uiplib/settings.py
uiplib/utils.py
uiplib/scrape/__init__.py
uiplib/scrape/onlineFetch.py
uiplib/scrape/scrape.py