Metadata-Version: 1.0
Name: UIP
Version: 0.0.3
Summary: A library to get new wallpapers.
Home-page: https://www.github.com/NIT-dgp/UIP
Author: uip-dev
Author-email: uip.developers@gmail.com
License: LICENSE
Platform: UNKNOWN
